geosupport/__init__.py
geosupport/config.py
geosupport/error.py
geosupport/function_info.py
geosupport/geosupport.py
geosupport/io.py
geosupport/platform_utils.py
geosupport/function_info/function_info.csv
geosupport/function_info/function_inputs.csv
geosupport/function_info/work_area_layouts/input/WA1.csv
geosupport/function_info/work_area_layouts/output/1A_BL_BN-long+tpad.csv
geosupport/function_info/work_area_layouts/output/1A_BL_BN-long.csv
geosupport/function_info/work_area_layouts/output/1A_BL_BN.csv
geosupport/function_info/work_area_layouts/output/1A_BL_BN_AP-extended.csv
geosupport/function_info/work_area_layouts/output/1A_BL_BN_AP-regular.csv
geosupport/function_info/work_area_layouts/output/1B.csv
geosupport/function_info/work_area_layouts/output/1_1E-extended.csv
geosupport/function_info/work_area_layouts/output/1_1E.csv
geosupport/function_info/work_area_layouts/output/2.csv
geosupport/function_info/work_area_layouts/output/2W.csv
geosupport/function_info/work_area_layouts/output/3-extended.csv
geosupport/function_info/work_area_layouts/output/3.csv
geosupport/function_info/work_area_layouts/output/3C-extended.csv
geosupport/function_info/work_area_layouts/output/3C.csv
geosupport/function_info/work_area_layouts/output/3S.csv
geosupport/function_info/work_area_layouts/output/AP.csv
geosupport/function_info/work_area_layouts/output/AUXSEG.csv
geosupport/function_info/work_area_layouts/output/BINs-tpad.csv
geosupport/function_info/work_area_layouts/output/BINs.csv
geosupport/function_info/work_area_layouts/output/INTERSECTION.csv
geosupport/function_info/work_area_layouts/output/LGI-extended.csv
geosupport/function_info/work_area_layouts/output/LGI.csv
geosupport/function_info/work_area_layouts/output/WA1.csv
tests/__init__.py
tests/testcase.py
tests/functional/__init__.py
tests/functional/test_call.py
tests/functional/test_call_alternate.py
tests/unit/__init__.py
tests/unit/test_error.py
tests/unit/test_function_info.py
tests/unit/test_help.py
python_geosupport-1.1.0.dist-info/METADATA
python_geosupport-1.1.0.dist-info/WHEEL
python_geosupport-1.1.0.dist-info/top_level.txt
python_geosupport-1.1.0.dist-info/RECORD
