Metadata-Version: 2.4
Name: python-geosupport
Version: 1.1.0
Summary: Python bindings for NYC Geosupport Desktop Edition
Home-page: https://github.com/ishiland/python-geosupport
Author: Ian Shiland, Jeremy Neiman
Author-email: ishiland@gmail.com
License: MIT
Project-URL: Bug Tracker, https://github.com/ishiland/python-geosupport/issues
Project-URL: Documentation, https://python-geosupport.readthedocs.io/en/latest/
Project-URL: Source Code, https://github.com/ishiland/python-geosupport
Keywords: NYC,geocoder,python-geosupport,geosupport
Classifier: Operating System :: Microsoft :: Windows
Classifier: Operating System :: POSIX :: Linux
Classifier: License :: OSI Approved :: MIT License
Classifier: Programming Language :: Python :: 3
Classifier: Programming Language :: Python :: 3.8
Classifier: Programming Language :: Python :: 3.9
Classifier: Programming Language :: Python :: 3.10
Classifier: Programming Language :: Python :: 3.11
Classifier: Programming Language :: Python :: 3.12
Requires-Python: >=3.8
Provides-Extra: dev
Requires-Dist: coverage; extra == "dev"
Requires-Dist: black==25.1.0; extra == "dev"
Dynamic: author
Dynamic: author-email
Dynamic: classifier
Dynamic: description
Dynamic: description-content-type
Dynamic: home-page
Dynamic: keywords
Dynamic: license
Dynamic: project-url
Dynamic: provides-extra
Dynamic: requires-python
Dynamic: summary
